{"id":"OP14-082","pack_id":"556114","name":"Oinkchuck","rarity":"Common","category":"Character","img_url":"../images/cardlist/card/OP14-082.png?251219","img_full_url":"https://asia-en.onepiece-cardgame.com/images/cardlist/card/OP14-082.png?251219","cost":2,"attributes":["Slash"],"power":3000,"counter":1000,"colors":["Black"],"block_number":4,"types":["Thriller Bark Pirates"],"effect":"[On K.O.] All of your {Thriller Bark Pirates} type Characters gain +4 cost until the end of your opponent's next End Phase.","trigger":"[Trigger] Play up to 1 {Thriller Bark Pirates} type Character card with a cost of 2 or less from your trash rested."}