{"id":"EB01-021_p1","pack_id":"556201","name":"Hannyabal (Parallel)","rarity":"Leader","category":"Leader","img_url":"../images/cardlist/card/EB01-021_p1.png?250912","img_full_url":"https://asia-en.onepiece-cardgame.com/images/cardlist/card/EB01-021_p1.png?250912","colors":["Blue","Purple"],"cost":4,"attributes":["Slash"],"power":5000,"counter":null,"types":["Impel Down"],"effect":"[End of Your Turn] You may return 1 of your {Impel Down} type Characters with a cost of 2 or more to the owner's hand: Add up to 1 DON!! card from your DON!! deck and set it as active.","trigger":null}